utile/Processor.py
utile/Sorter.py
utile/Threader.py
utile/Timer.py
utile/__init__.py
utile/rusty_sorter.pyd
utile/timsort/Cargo.lock
utile/timsort/Cargo.toml
utile/timsort/MANIFEST.in
utile/timsort/pyproject.toml
utile/timsort/setup.py
utile/timsort/build/lib.win-amd64-3.8/timsort/__init__.py
utile/timsort/build/lib.win-amd64-3.8/timsort/_timsort.cp38-win_amd64.pyd
utile/timsort/dist/timsort-0.1.0-cp38-cp38-win_amd64.whl
utile/timsort/dist/timsort-0.1.0-py3.8-win-amd64.egg
utile/timsort/src/lib.rs
utile/timsort/test/test_sorter.py
utile/timsort/timsort/__init__.py
utile/timsort/timsort.egg-info/PKG-INFO
utile/timsort/timsort.egg-info/SOURCES.txt
utile/timsort/timsort.egg-info/dependency_links.txt
utile/timsort/timsort.egg-info/not-zip-safe
utile/timsort/timsort.egg-info/top_level.txt
utile-1.1.dist-info/LICENSE
utile-1.1.dist-info/METADATA
utile-1.1.dist-info/WHEEL
utile-1.1.dist-info/top_level.txt
utile-1.1.dist-info/RECORD
