Metadata-Version: 2.1
Name: utile
Version: 1.1
Summary: The python package which eases your <codeflow> using decorators
Home-page: https://github.com/j0fiN/utile.git
Author: Jofin F Archbald
Author-email: jofinfab@gmail.com
License: UNKNOWN
Project-URL: Documentation, https://utile.readthedocs.io/
Project-URL: Say Thanks!, https://jofin-f-archbald.herokuapp.com/
Project-URL: Source, https://github.com/j0fiN/utile/
Platform: UNKNOWN
Classifier: Programming Language :: Python :: 3
Classifier: License :: OSI Approved :: MIT License
Classifier: Operating System :: OS Independent
Requires-Python: >=3.6
Requires-Dist: timsortyer
